otel_lean_tracer/__init__.py
otel_lean_tracer/attributes/__init__.py
otel_lean_tracer/attributes/lean_attributes.py
otel_lean_tracer/exporters/__init__.py
otel_lean_tracer/exporters/factory.py
otel_lean_tracer/exporters/tempo.py
otel_lean_tracer/mixins/__init__.py
otel_lean_tracer/mixins/flow_mixin.py
otel_lean_tracer/processors/__init__.py
otel_lean_tracer/processors/lean_processor.py
otel_lean_tracer/utils/__init__.py
otel_lean_tracer/utils/context.py
otel_lean_tracer/utils/cost.py
otel_lean_tracer-0.0.1.dist-info/METADATA
otel_lean_tracer-0.0.1.dist-info/WHEEL
otel_lean_tracer-0.0.1.dist-info/top_level.txt
otel_lean_tracer-0.0.1.dist-info/RECORD
