Metadata-Version: 2.4
Name: otel-lean-tracer
Version: 0.0.1
Summary: OpenTelemetry-compatible tracing library that adds Lean Production KPIs to LLM/Agent execution traces
Requires-Python: >=3.11
Requires-Dist: opentelemetry-api>=1.25.0
Requires-Dist: opentelemetry-sdk>=1.25.0
Requires-Dist: opentelemetry-exporter-otlp>=1.25.0
Requires-Dist: pydantic>=2.0.0
Requires-Dist: python-dotenv>=1.0.0
Requires-Dist: click>=8.1.0
Provides-Extra: dev
Requires-Dist: pytest>=8.0.0; extra == "dev"
Requires-Dist: pytest-cov>=4.1.0; extra == "dev"
Requires-Dist: pytest-asyncio>=0.21.0; extra == "dev"
